solace/__init__.py
solace/app_config_schema.yml
solace/cli/__init__.py
solace/config.py
solace/config.py.txt
solace/context.py
solace/exceptions.py
solace/flow.py
solace/importer.py
solace/model.py
solace/response.py
solace/solace-constructor.py.txt
solace/store.py
solace/templating.py
solace/utils/ymlutils.py
solace/validator.py
solace-0.1.22.dist-info/entry_points.txt
solace-0.1.22.dist-info/WHEEL
solace-0.1.22.dist-info/METADATA
solace-0.1.22.dist-info/RECORD
